rex_main/__init__.py
rex_main/audio_stream.py
rex_main/benchmark.py
rex_main/cli.py
rex_main/commands.py
rex_main/config.py
rex_main/default_config.yaml
rex_main/fast_vad.py
rex_main/matcher.py
rex_main/metrics.py
rex_main/metrics_printer.py
rex_main/rex.py
rex_main/setup_wizard.py
rex_main/steelseries.py
rex_main/vad_stream.py
rex_main/whisper_worker.py
rex_main/dashboard/__init__.py
rex_main/dashboard/server.py
rex_main/dashboard/static/dashboard.css
rex_main/dashboard/static/dashboard.js
rex_main/dashboard/static/index.html
rex_voice_assistant-0.2.1.dist-info/METADATA
rex_voice_assistant-0.2.1.dist-info/WHEEL
rex_voice_assistant-0.2.1.dist-info/entry_points.txt
rex_voice_assistant-0.2.1.dist-info/top_level.txt
rex_voice_assistant-0.2.1.dist-info/RECORD
