Metadata-Version: 2.4
Name: rex-voice-assistant
Version: 0.2.1
Summary: Offline voice assistant for controlling YouTube Music Desktop and Spotify
Author-email: David Antolick <david.antolick@gmail.com>
License-Expression: MIT
Project-URL: Homepage, https://github.com/David-Antolick/rex_voice_assistant
Keywords: voice-assistant,whisper,spotify,youtube-music,speech-recognition
Classifier: Development Status :: 4 - Beta
Classifier: Environment :: Console
Classifier: Intended Audience :: End Users/Desktop
Classifier: Operating System :: Microsoft :: Windows
Classifier: Programming Language :: Python :: 3
Classifier: Programming Language :: Python :: 3.10
Classifier: Programming Language :: Python :: 3.11
Classifier: Programming Language :: Python :: 3.12
Classifier: Topic :: Multimedia :: Sound/Audio :: Speech
Requires-Python: >=3.10
Requires-Dist: numpy>=1.24
Requires-Dist: scipy
Requires-Dist: sounddevice
Requires-Dist: soundfile
Requires-Dist: faster-whisper>=0.10
Requires-Dist: silero-vad
Requires-Dist: torch>=2.0
Requires-Dist: torchaudio
Requires-Dist: pyyaml
Requires-Dist: requests
Requires-Dist: ytmusicapi
Requires-Dist: spotipy
Requires-Dist: python-dotenv
Requires-Dist: click>=8.0
Requires-Dist: rich>=13.0
Requires-Dist: keyring
Provides-Extra: cuda
Requires-Dist: nvidia-cudnn-cu12==9.5.1.17; extra == "cuda"
Provides-Extra: dashboard
Requires-Dist: fastapi>=0.100; extra == "dashboard"
Requires-Dist: uvicorn[standard]>=0.23; extra == "dashboard"
Requires-Dist: websockets>=11.0; extra == "dashboard"
Provides-Extra: benchmark
Requires-Dist: psutil>=5.9; extra == "benchmark"
Requires-Dist: pynvml>=11.5; extra == "benchmark"
Provides-Extra: integrations
Requires-Dist: pypresence>=4.3; extra == "integrations"
Requires-Dist: obsws-python>=1.6; extra == "integrations"
Requires-Dist: aiohttp>=3.8; extra == "integrations"
Provides-Extra: streamer
Requires-Dist: rex-voice-assistant[benchmark,dashboard,integrations]; extra == "streamer"
Provides-Extra: dev
Requires-Dist: pytest; extra == "dev"
Requires-Dist: pytest-asyncio; extra == "dev"
Requires-Dist: black; extra == "dev"
Requires-Dist: ruff; extra == "dev"
